{
  "status": "alert",
  "summary": "Critical pH and TDS levels require immediate attention.",
  "insights": [
    {
      "metric": "ph",
      "trend": "low average",
      "recommendation": "Buffer up the pH to reach the ideal range."
    },
    {
      "metric": "tds",
      "trend": "high average",
      "recommendation": "Perform a partial water change to lower TDS levels."
    },
    {
      "metric": "temp",
      "trend": "acceptable range",
      "recommendation": "Monitor temperature to ensure it remains within the ideal range."
    }
  ],
  "timestamp": "2025-08-25T01:45:16.928753+00:00"
}